traceon/__init__.py
traceon/excitation.py
traceon/field.py
traceon/focus.py
traceon/geometry.py
traceon/logging.py
traceon/mesher.py
traceon/plotting.py
traceon/solver.py
traceon/tracing.py
traceon/util.py
traceon/backend/__init__.py
traceon/backend/definitions.c
traceon/backend/elliptic.c
traceon/backend/kronrod.c
traceon/backend/radial.c
traceon/backend/radial_ring.c
traceon/backend/three_d.c
traceon/backend/traceon-backend.c
traceon/backend/traceon_backend.abi3.so
traceon/backend/tracing.c
traceon/backend/triangle.c
traceon/backend/utilities_2d.c
traceon/backend/utilities_3d.c
traceon-0.9.0.dist-info/LICENSE.txt
traceon-0.9.0.dist-info/METADATA
traceon-0.9.0.dist-info/WHEEL
traceon-0.9.0.dist-info/top_level.txt
traceon-0.9.0.dist-info/RECORD
