Metadata-Version: 2.1
Name: traceon
Version: 0.9.0
Summary: Solver and tracer for electrostatic problems
Home-page: https://github.com/leon-vv/Traceon
Author: Léon van Velzen
Author-email: leonvanvelzen@protonmail.com
License: MPL 2.0
Project-URL: Documentation, https://leon.science/traceon
Project-URL: Code, https://github.com/leon-vv/traceon
Project-URL: Issues, https://github.com/leon-vv/traceon/issues
Keywords: boundary element method,BEM,electrostatic,electromagnetic,electron microscope,electron,tracing,particle,tracer,electron optics
Requires-Python: >=3.7
License-File: LICENSE.txt
Requires-Dist: matplotlib
Requires-Dist: vedo
Requires-Dist: numpy
Requires-Dist: scipy
Requires-Dist: meshio
